kuasarr/__init__.py
kuasarr/__main__.py
kuasarr/version.json
kuasarr/api/__init__.py
kuasarr/api/manual_links.py
kuasarr/api/search.py
kuasarr/api/arr/__init__.py
kuasarr/api/captcha/__init__.py
kuasarr/api/captcha/helpers.py
kuasarr/api/captcha/main_routes.py
kuasarr/api/captcha/provider_routes.py
kuasarr/api/captcha/proxy_routes.py
kuasarr/api/captcha/routes.py
kuasarr/api/captcha/submission_routes.py
kuasarr/api/captcha/ui_components.py
kuasarr/api/config/__init__.py
kuasarr/api/dbc/__init__.py
kuasarr/api/hosters/__init__.py
kuasarr/api/statistics/__init__.py
kuasarr/downloads/__init__.py
kuasarr/downloads/manual_jobs.py
kuasarr/downloads/postprocessing.py
kuasarr/downloads/linkcrypters/__init__.py
kuasarr/downloads/linkcrypters/al.py
kuasarr/downloads/linkcrypters/filecrypt.py
kuasarr/downloads/linkcrypters/hide.py
kuasarr/downloads/linkcrypters/keeplinks.py
kuasarr/downloads/packages/__init__.py
kuasarr/downloads/sources/__init__.py
kuasarr/downloads/sources/ad.py
kuasarr/downloads/sources/al.py
kuasarr/downloads/sources/by.py
kuasarr/downloads/sources/dd.py
kuasarr/downloads/sources/dl.py
kuasarr/downloads/sources/dl_new.py
kuasarr/downloads/sources/dl_old_complex.py
kuasarr/downloads/sources/dt.py
kuasarr/downloads/sources/dw.py
kuasarr/downloads/sources/he.py
kuasarr/downloads/sources/mb.py
kuasarr/downloads/sources/nk.py
kuasarr/downloads/sources/nx.py
kuasarr/downloads/sources/sf.py
kuasarr/downloads/sources/sl.py
kuasarr/downloads/sources/wd.py
kuasarr/downloads/sources/wx.py
kuasarr/providers/__init__.py
kuasarr/providers/common_functions.py
kuasarr/providers/hosters.py
kuasarr/providers/imdb_metadata.py
kuasarr/providers/jdownloader.py
kuasarr/providers/log.py
kuasarr/providers/magazine.py
kuasarr/providers/myjd_api.py
kuasarr/providers/notifications.py
kuasarr/providers/obfuscated.py
kuasarr/providers/pwa_installer.py
kuasarr/providers/shared_state.py
kuasarr/providers/statistics.py
kuasarr/providers/utils.py
kuasarr/providers/validation.py
kuasarr-1.11.4.dist-info/licenses/LICENSE
kuasarr-1.11.4.dist-info/METADATA
kuasarr-1.11.4.dist-info/WHEEL
kuasarr-1.11.4.dist-info/entry_points.txt
kuasarr-1.11.4.dist-info/top_level.txt
kuasarr-1.11.4.dist-info/RECORD
