Metadata-Version: 2.4
Name: kuasarr
Version: 1.11.4
Summary: kuasarr connects JDownloader with Radarr, Sonarr and LazyLibrarian. It also decrypts links protected by CAPTCHAs, using an additional CaptchaSolverr.
Home-page: https://github.com/rix1337/Kuasarr
Author: weedo078
Author-email: weedo0780@protonmail.com
License: MIT
Classifier: Programming Language :: Python :: 3
Classifier: Operating System :: OS Independent
License-File: LICENSE
Requires-Dist: beautifulsoup4>=4.14.2
Requires-Dist: bottle>=0.13.4
Requires-Dist: deathbycaptcha-official>=4.6.0
Requires-Dist: dukpy>=0.5.0
Requires-Dist: pillow>=12.0.0
Requires-Dist: pycryptodomex>=3.23.0
Requires-Dist: requests>=2.32.5
Requires-Dist: urllib3>=2.6.0
Dynamic: author
Dynamic: author-email
Dynamic: classifier
Dynamic: description
Dynamic: description-content-type
Dynamic: home-page
Dynamic: license
Dynamic: license-file
Dynamic: requires-dist
Dynamic: summary
